rfk101py/__init__.py
rfk101py/rfk101.py
rfk101py/rfk101py.py
rfk101py/test.py
rfk101py-0.0.1.dist-info/LICENSE
rfk101py-0.0.1.dist-info/METADATA
rfk101py-0.0.1.dist-info/WHEEL
rfk101py-0.0.1.dist-info/top_level.txt
rfk101py-0.0.1.dist-info/RECORD
