Metadata-Version: 2.1
Name: rfk101py
Version: 0.0.1
Summary: RFK101 Proximity card reader over Ethernet
Home-page: https://github.com/dubnom/rfk101py
Author: Michael Dubno
Author-email: michael@dubno.com
License: UNKNOWN
Platform: UNKNOWN
Classifier: Programming Language :: Python :: 3
Classifier: License :: OSI Approved :: MIT License
Classifier: Operating System :: OS Independent
